applm/__init__.py
applm/main.py
applm/models/__init__.py
applm/models/base.py
applm/models/cohere.py
applm/models/dbrx.py
applm/models/deepseek_v2.py
applm/models/gemma.py
applm/models/gemma2.py
applm/models/gpt2.py
applm/models/gpt_bigcode.py
applm/models/gpt_neox.py
applm/models/internlm2.py
applm/models/llama.py
applm/models/minicpm.py
applm/models/mixtral.py
applm/models/olmo.py
applm/models/openelm.py
applm/models/phi.py
applm/models/phi3.py
applm/models/phi3small.py
applm/models/phixtral.py
applm/models/plamo.py
applm/models/qwen.py
applm/models/qwen2.py
applm/models/qwen2_moe.py
applm/models/recurrent_gemma.py
applm/models/stablelm.py
applm/models/starcoder2.py
applm/models/su_rope.py
applm/models/switch_layers.py
applm/utils/apply_repetition_penalty.py
applm/utils/generate.py
applm/utils/generate_step.py
applm/utils/get_classes.py
applm/utils/get_model_path.py
applm/utils/load.py
applm/utils/load_model.py
applm/utils/models/KVCache.py
applm/utils/models/switch_layers/QuantizedSwitchLinear.py
applm/utils/models/switch_layers/SwitchGLU.py
applm/utils/models/switch_layers/SwitchLinear.py
applm/utils/models/switch_layers/SwitchMLP.py
applm/utils/sample_utils/top_p_sampling.py
applm/utils/tokenizer/BPEStreamingDetokenizer.py
applm/utils/tokenizer/NaiveStreamingDetokenizer.py
applm/utils/tokenizer/REPLACEMENT_CHAR.py
applm/utils/tokenizer/SPMStreamingDetokenizer.py
applm/utils/tokenizer/StreamingDetokenizer.py
applm/utils/tokenizer/is_valid_decoder.py
applm/utils/tokenizer/load.py
applm/utils/tokenizer/wrapper.py
applm/utils/tuner/LoRALinear.py
applm/utils/tuner/LoRASwitchLinear.py
applm/utils/tuner/apply_lora_layers.py
applm/utils/tuner/dora.py
applm/utils/tuner/linear_to_lora_layers.py
applm-0.0.51.dist-info/LICENSE
applm-0.0.51.dist-info/METADATA
applm-0.0.51.dist-info/WHEEL
applm-0.0.51.dist-info/top_level.txt
applm-0.0.51.dist-info/RECORD
