Metadata-Version: 2.1
Name: applm
Version: 0.0.51
Summary: Language Model Tools for Apple Silicon
Author: Jonathan Dobson
Project-URL: Homepage, https://github.com/Jonathan-Dobson/applm
Project-URL: Issues, https://github.com/Jonathan-Dobson/applm/issues
Classifier: Programming Language :: Python :: 3
Classifier: License :: OSI Approved :: MIT License
Classifier: Operating System :: MacOS :: MacOS X
Requires-Python: >=3.8
License-File: LICENSE
